miscutils/__init__.py
miscutils/base.py
miscutils/context.py
miscutils/functions.py
miscutils/mixin.py
miscutils/parser.py
pymiscutils-0.3.14.dist-info/LICENSE
pymiscutils-0.3.14.dist-info/METADATA
pymiscutils-0.3.14.dist-info/WHEEL
pymiscutils-0.3.14.dist-info/top_level.txt
pymiscutils-0.3.14.dist-info/RECORD
