Metadata-Version: 2.1
Name: pymiscutils
Version: 0.3.14
Summary: Provides a wide range of useful classes and functions.
Home-page: https://github.com/matthewgdv/miscutils
Author: Matt GdV
Author-email: matthewgdv@gmail.com
License: MIT
Platform: UNKNOWN
Classifier: Development Status :: 3 - Alpha
Classifier: Intended Audience :: Developers
Classifier: Programming Language :: Python :: 3.8
